[{"id": 197895, "title": "Reducing Barriers to Learning Act of 2009", "url": "https://legiscan.com/US/bill/HB3800/2009"}, {"id": 195705, "title": "Student Support Act", "url": "https://legiscan.com/US/bill/HB1338/2009"}, {"id": 342227, "title": "Student Support Act", "url": "https://legiscan.com/US/bill/HB3169/2011"}, {"id": 330105, "title": "Successful, Safe, and Healthy Students Act of 2011", "url": "https://legiscan.com/US/bill/SB919/2011"}, {"id": 334514, "title": "Reducing Barriers to Learning Act of 2011", "url": "https://legiscan.com/US/bill/HB1995/2011"}, {"id": 341392, "title": "Empowering Local Educational Decisionmaking Act of 2011", "url": "https://legiscan.com/US/bill/SB1569/2011"}, {"id": 463004, "title": "Student Support Act", "url": "https://legiscan.com/US/bill/HB320/2013"}, {"id": 564929, "title": "Successful, Safe, and Healthy Students Act of 2013", "url": "https://legiscan.com/US/bill/HB3122/2013"}, {"id": 558294, "title": "Every Child Ready for College or Career Act of 2013", "url": "https://legiscan.com/US/bill/SB1101/2013"}, {"id": 537696, "title": "Helping Educators Support All Students Act", "url": "https://legiscan.com/US/bill/SB648/2013"}, {"id": 552148, "title": "Reducing Barriers to Learning Act of 2013", "url": "https://legiscan.com/US/bill/HB1940/2013"}, {"id": 557796, "title": "Strengthening America's Schools Act of 2013", "url": "https://legiscan.com/US/bill/SB1094/2013"}, {"id": 551496, "title": "Partnerships for Achieving Student Success Act", "url": "https://legiscan.com/US/bill/HB1854/2013"}, {"id": 571544, "title": "S.O.S. Act of 2013", "url": "https://legiscan.com/US/bill/HB3536/2013"}, {"id": 780059, "title": "Student Support Act", "url": "https://legiscan.com/US/bill/HB2375/2015"}, {"id": 780052, "title": "Reducing Barriers to Learning Act of 2015", "url": "https://legiscan.com/US/bill/HB2378/2015"}, {"id": 860773, "title": "S.O.S. Act of 2016 Support Our Students Act of 2016", "url": "https://legiscan.com/US/bill/HB4716/2015"}, {"id": 1102766, "title": "School Safety and Mental Health Services Improvement Act of 2018", "url": "https://legiscan.com/US/bill/SB2513/2017"}, {"id": 1126215, "title": "Elementary and Secondary School Counseling Act", "url": "https://legiscan.com/US/bill/HB6775/2017"}, {"id": 1107320, "title": "Supporting Teachers and Safe Students Act", "url": "https://legiscan.com/US/bill/HB5324/2017"}, {"id": 1119797, "title": "Increasing Access to Mental Health in Schools Act", "url": "https://legiscan.com/US/bill/SB2934/2017"}, {"id": 1384200, "title": "Youth Mental Health Services Act of 2020", "url": "https://legiscan.com/US/bill/SB4930/2019"}, {"id": 1275642, "title": "Student Support Act", "url": "https://legiscan.com/US/bill/HB4525/2019"}, {"id": 1286871, "title": "Ending PUSHOUT Act of 2019 Ending Punitive, Unfair, School-based Harm that is Overt and Unresponsive to Trauma Act of 2019", "url": "https://legiscan.com/US/bill/HB5325/2019"}, {"id": 1275147, "title": "Timely Mental Health for Foster Youth Act", "url": "https://legiscan.com/US/bill/HB4420/2019"}, {"id": 1275018, "title": "Elementary and Secondary School Counseling Act", "url": "https://legiscan.com/US/bill/HB4381/2019"}, {"id": 1264464, "title": "Increasing Access to Mental Health in Schools Act", "url": "https://legiscan.com/US/bill/SB1642/2019"}, {"id": 1223733, "title": "Youth Mental Health Services Act of 2019", "url": "https://legiscan.com/US/bill/HB1395/2019"}, {"id": 1272127, "title": "Mental Health in Schools Excellence Program Act of 2019", "url": "https://legiscan.com/US/bill/HB4025/2019"}]